{
  "meta_title": "",
  "meta_description": "",
  "sections": [
    {
      "type": "banner-slider",
      "autoplay": 9000,
      "full_width": true,
      "slides": [
        {
          "start": "",
          "end": "",
          "img": "/img/uploads/ag25outono.jpg",
          "mobile_img": "/img/uploads/aagoutono25mobile.jpg"
        },
        {
          "start": "",
          "end": "",
          "img": "/img/uploads/lcoutinv24_v2.jpg"
        }
      ]
    },
    {
      "type": "responsive-banner",
      "img": "/img/uploads/modelotarja.png",
      "mobile_img": "/img/uploads/modelotarja.png"
    },
    {
      "type": "info-bar",
      "enabled": false
    },
    {
      "type": "collection-shelf",
      "shuffle": true,
      "collection_id": null,
      "sort": "news",
      "title": "",
      "headless": false,
      "limit": 12,
      "page": 1
    },
    {
      "type": "page-title",
      "title": "Loja demo da E-Com Plus",
      "description": "Loja de demonstração e testes da plataforma E-Com Plus e Storefront. Todos os produtos, preços e informações são meramente ilustrativos."
    }
  ]
}